agp_py/__init__.py
agp_py/main.py
agp_py/assets/__init__.py
agp_py/assets/parts.py
agp_py/assets/traits.py
agp_py/models/__init__.py
agp_py/models/mappings.py
agp_py-0.1.2.dist-info/LICENSE
agp_py-0.1.2.dist-info/METADATA
agp_py-0.1.2.dist-info/WHEEL
agp_py-0.1.2.dist-info/top_level.txt
agp_py-0.1.2.dist-info/RECORD
