Metadata-Version: 2.1
Name: agp-py
Version: 0.1.2
Summary: Gene parser for Axie Infinity
Home-page: https://github.com/Stiggu/agp-py
Author: Abel Mundarain
Author-email: stiggu@protonmail.com
License: UNKNOWN
Project-URL: Bug Tracker, https://github.com/Stiggu/agp-py/issues
Keywords: python,axie infinity
Platform: UNKNOWN
Classifier: Development Status :: 4 - Beta
Classifier: Programming Language :: Python :: 3
Classifier: Operating System :: OS Independent
License-File: LICENSE
